awesome_tool/__init__.py
awesome_tool/__main__.py
awesome_tool/cli.py
awesome_tool-0.1.3.dist-info/licenses/LICENSE
awesome_tool-0.1.3.dist-info/METADATA
awesome_tool-0.1.3.dist-info/WHEEL
awesome_tool-0.1.3.dist-info/entry_points.txt
awesome_tool-0.1.3.dist-info/top_level.txt
awesome_tool-0.1.3.dist-info/RECORD
