Metadata-Version: 2.4
Name: awesome_tool
Version: 0.1.3
License-File: LICENSE
Requires-Dist: mcp
Dynamic: license-file
Dynamic: requires-dist
